dbt/adapters/mysql/__init__.py
dbt/adapters/mysql/__version__.py
dbt/adapters/mysql/column.py
dbt/adapters/mysql/connections.py
dbt/adapters/mysql/impl.py
dbt/adapters/mysql/relation.py
dbt/adapters/mysql5/__init__.py
dbt/adapters/mysql5/__version__.py
dbt/adapters/mysql5/column.py
dbt/adapters/mysql5/connections.py
dbt/adapters/mysql5/impl.py
dbt/adapters/mysql5/relation.py
dbt/include/mysql/__init__.py
dbt/include/mysql/dbt_project.yml
dbt/include/mysql/macros/adapters.sql
dbt/include/mysql/macros/catalog.sql
dbt/include/mysql/macros/materializations/incremental/incremental.sql
dbt/include/mysql/macros/materializations/incremental/merge.sql
dbt/include/mysql/macros/materializations/seed/seed.sql
dbt/include/mysql/macros/materializations/snapshot/snapshot.sql
dbt/include/mysql/macros/materializations/snapshot/snapshot_merge.sql
dbt/include/mysql/macros/materializations/snapshot/strategies.sql
dbt/include/mysql/macros/materializations/table/table.sql
dbt/include/mysql/sample_profiles.yml
dbt/include/mysql5/__init__.py
dbt/include/mysql5/dbt_project.yml
dbt/include/mysql5/macros/adapters.sql
dbt/include/mysql5/macros/catalog.sql
dbt/include/mysql5/macros/materializations/seed/seed.sql
dbt/include/mysql5/macros/materializations/snapshot/snapshot.sql
dbt/include/mysql5/macros/materializations/snapshot/snapshot_merge.sql
dbt/include/mysql5/macros/materializations/snapshot/strategies.sql
dbt/include/mysql5/sample_profiles.yml
dbt_mysql_adapter-0.19.0.dist-info/LICENSE
dbt_mysql_adapter-0.19.0.dist-info/WHEEL
dbt_mysql_adapter-0.19.0.dist-info/METADATA
dbt_mysql_adapter-0.19.0.dist-info/RECORD
