Metadata-Version: 2.1
Name: dbt-mysql-adapter
Version: 0.19.0
Summary: The MySQL adapter plugin for dbt (data build tool)
Home-page: https://github.com/julianopiovezan/dbt-mysql-adapter
License: Apache-2.0
Keywords: dbt-mysql,adapter,dbt,mysql
Author: Juliano Benvenuto Piovezan
Author-email: piovezan.juliano@gmail.com
Requires-Python: >=3.6.3
Classifier: Development Status :: 3 - Alpha
Classifier: License :: OSI Approved :: Apache Software License
Classifier: Operating System :: MacOS :: MacOS X
Classifier: Operating System :: Microsoft :: Windows
Classifier: Operating System :: POSIX :: Linux
Classifier: Programming Language :: Python :: 3
Classifier: Programming Language :: Python :: 3.10
Classifier: Programming Language :: Python :: 3.6
Classifier: Programming Language :: Python :: 3.7
Classifier: Programming Language :: Python :: 3.8
Classifier: Programming Language :: Python :: 3.9
Requires-Dist: dbt-core (==0.19.0)
Requires-Dist: mysql-connector-python (>=8.0.22,<8.1.0)
Requires-Dist: wrapt (==1.13.3)
